LICENSE
README.md
setup.py
pylinreglib/BaseLRM.py
pylinreglib/__init__.py
pylinreglib/clrm.py
pylinreglib/lrm.py
pylinreglib/mlrm.py
pylinreglib.egg-info/PKG-INFO
pylinreglib.egg-info/SOURCES.txt
pylinreglib.egg-info/dependency_links.txt
pylinreglib.egg-info/requires.txt
pylinreglib.egg-info/top_level.txt