Metadata-Version: 2.1
Name: pylinreglib
Version: 0.1.2
Summary: Biblioteca de libre desarrollo especializada en regresiones lineales
Home-page: https://github.com/SamuelOrtizT/pylinreglib
Author: Samuel Ortiz Toro
Author-email: saortizt@unal.edu.co
License: MIT
Classifier: Programming Language :: Python :: 3
Classifier: Programming Language :: Python :: 3.7
Classifier: License :: OSI Approved :: MIT License
Classifier: Operating System :: OS Independent
Classifier: Intended Audience :: Science/Research
Classifier: Topic :: Scientific/Engineering :: Artificial Intelligence
Classifier: Topic :: Scientific/Engineering :: Mathematics
Classifier: Topic :: Software Development :: Libraries :: Python Modules
Classifier: Development Status :: 3 - Alpha
Requires-Python: >=3.8
License-File: LICENSE
